inline_snapshot/__init__.py
inline_snapshot/_align.py
inline_snapshot/_change.py
inline_snapshot/_code_repr.py
inline_snapshot/_compare_context.py
inline_snapshot/_config.py
inline_snapshot/_exceptions.py
inline_snapshot/_fix_assert.py
inline_snapshot/_flags.py
inline_snapshot/_format.py
inline_snapshot/_get_snapshot_value.py
inline_snapshot/_global_state.py
inline_snapshot/_inline_snapshot.py
inline_snapshot/_is.py
inline_snapshot/_problems.py
inline_snapshot/_rewrite_code.py
inline_snapshot/_sentinels.py
inline_snapshot/_snapshot_session.py
inline_snapshot/_source_file.py
inline_snapshot/_types.py
inline_snapshot/_unmanaged.py
inline_snapshot/_utils.py
inline_snapshot/extra.py
inline_snapshot/fix_pytest_diff.py
inline_snapshot/py.typed
inline_snapshot/pydantic_fix.py
inline_snapshot/pytest_plugin.py
inline_snapshot/syntax_warnings.py
inline_snapshot/version.py
inline_snapshot/_adapter/__init__.py
inline_snapshot/_adapter/adapter.py
inline_snapshot/_adapter/dict_adapter.py
inline_snapshot/_adapter/generic_call_adapter.py
inline_snapshot/_adapter/sequence_adapter.py
inline_snapshot/_adapter/value_adapter.py
inline_snapshot/_external/__init__.py
inline_snapshot/_external/_diff.py
inline_snapshot/_external/_external.py
inline_snapshot/_external/_external_base.py
inline_snapshot/_external/_external_file.py
inline_snapshot/_external/_external_location.py
inline_snapshot/_external/_find_external.py
inline_snapshot/_external/_outsource.py
inline_snapshot/_external/_format/__init__.py
inline_snapshot/_external/_format/_binary.py
inline_snapshot/_external/_format/_json.py
inline_snapshot/_external/_format/_protocol.py
inline_snapshot/_external/_format/_text.py
inline_snapshot/_external/_storage/__init__.py
inline_snapshot/_external/_storage/_hash.py
inline_snapshot/_external/_storage/_protocol.py
inline_snapshot/_external/_storage/_uuid.py
inline_snapshot/_snapshot/collection_value.py
inline_snapshot/_snapshot/dict_value.py
inline_snapshot/_snapshot/eq_value.py
inline_snapshot-0.31.1.dist-info/METADATA
inline_snapshot-0.31.1.dist-info/WHEEL
inline_snapshot-0.31.1.dist-info/entry_points.txt
inline_snapshot-0.31.1.dist-info/licenses/LICENSE
inline_snapshot-0.31.1.dist-info/RECORD
