Metadata-Version: 2.4
Name: inline-snapshot
Version: 0.31.1
Summary: golden master/snapshot/approval testing library which puts the values right into your source code
Project-URL: Changelog, https://15r10nk.github.io/inline-snapshot/latest/changelog/
Project-URL: Discussions, https://github.com/15r10nk/inline-snapshots/discussions
Project-URL: Documentation, https://15r10nk.github.io/inline-snapshot/latest
Project-URL: Funding, https://github.com/sponsors/15r10nk
Project-URL: Homepage, https://15r10nk.github.io/inline-snapshot/latest
Project-URL: Issues, https://github.com/15r10nk/inline-snapshots/issues
Project-URL: Repository, https://github.com/15r10nk/inline-snapshot/
Author-email: Frank Hoffmann <15r10nk-git@polarbit.de>
License-File: LICENSE
Classifier: Development Status :: 4 - Beta
Classifier: Framework :: Pytest
Classifier: Intended Audience :: Developers
Classifier: License :: OSI Approved :: MIT License
Classifier: Operating System :: OS Independent
Classifier: Programming Language :: Python
Classifier: Programming Language :: Python :: 3.8
Classifier: Programming Language :: Python :: 3.9
Classifier: Programming Language :: Python :: 3.10
Classifier: Programming Language :: Python :: 3.11
Classifier: Programming Language :: Python :: 3.12
Classifier: Programming Language :: Python :: 3.13
Classifier: Programming Language :: Python :: 3.14
Classifier: Programming Language :: Python :: Implementation :: CPython
Classifier: Programming Language :: Python :: Implementation :: PyPy
Classifier: Topic :: Software Development :: Testing
Requires-Python: >=3.8
Requires-Dist: asttokens>=2.0.5
Requires-Dist: executing>=2.2.0
Requires-Dist: pytest>=8.3.4
Requires-Dist: rich>=13.7.1
Requires-Dist: tomli>=2.0.0; python_version < '3.11'
Provides-Extra: black
Requires-Dist: black>=23.3.0; extra == 'black'
Provides-Extra: dirty-equals
Requires-Dist: dirty-equals>=0.9.0; extra == 'dirty-equals'
